{
    "name": "Dataset 5",
    "description": "Dataset 5",
    "date": "2022-09-14",
    "patch": "3.19.0",
    "sources": [
        {
            "name": "Google Sheet",
            "url": "https://docs.google.com/spreadsheets/d/1-bQ_n1M67Tu2Mch7zv-iNBAmxaLvL6-vZJ3EDF_fJc8/edit?gid=0#gid=0",
            "author": "Lextra"
        },
        {
            "name": "Discord Thread",
            "url": "https://discord.com/channels/991073626721763429/1019681836584161402",
            "author": "FallenAng3L"
        }
    ],
    "inputItems": [
        {
            "id": "lucent"
        }
    ],
    "items": [
        {
            "id": "jagged",
            "count": 117
        },
        {
            "id": "dense",
            "count": 110
        },
        {
            "id": "frigid",
            "count": 108
        },
        {
            "id": "abberant",
            "count": 116
        },
        {
            "id": "scorched",
            "count": 89
        },
        {
            "id": "metalic",
            "count": 106
        },
        {
            "id": "pristine",
            "count": 126
        },
        {
            "id": "bound",
            "count": 25
        },
        {
            "id": "corroded",
            "count": 30
        },
        {
            "id": "perfect",
            "count": 20
        },
        {
            "id": "prismatic",
            "count": 20
        },
        {
            "id": "deft",
            "count": 16
        },
        {
            "id": "aetheric",
            "count": 23
        },
        {
            "id": "serrated",
            "count": 24
        },
        {
            "id": "shuddering",
            "count": 39
        },
        {
            "id": "gilded",
            "count": 1
        },
        {
            "id": "fundamental",
            "count": 23
        },
        {
            "id": "sanctified",
            "count": 1
        },
        {
            "id": "faceted",
            "count": 0
        },
        {
            "id": "fractured",
            "count": 2
        },
        {
            "id": "hollow",
            "count": 1
        },
        {
            "id": "glyphic",
            "count": 3
        },
        {
            "id": "bloodstained",
            "count": 0
        },
        {
            "id": "tangled",
            "count": 0
        }
    ]
}
